auto_intersphinx/__init__.py
auto_intersphinx/catalog.json
auto_intersphinx/catalog.py
auto_intersphinx/check_packages.py
auto_intersphinx/cli.py
auto_intersphinx/dump_objects.py
auto_intersphinx/update_catalog.py
auto_intersphinx-1.3.0.dist-info/METADATA
auto_intersphinx-1.3.0.dist-info/WHEEL
auto_intersphinx-1.3.0.dist-info/entry_points.txt
auto_intersphinx-1.3.0.dist-info/RECORD
