Metadata-Version: 2.4
Name: auto-intersphinx
Version: 1.3.0
Summary: Automatic links direct project dependencies to the intersphinx catalog
Project-URL: documentation, https://auto-intersphinx.readthedocs.io/en/latest/
Project-URL: homepage, https://pypi.org/project/auto-intersphinx
Project-URL: repository, https://github.com/idiap/auto-intersphinx
Project-URL: changelog, https://github.com/idiap/auto-intersphinx/releases
Author-email: Andre Anjos <andre.anjos@idiap.ch>
License-Expression: BSD-3-Clause
Classifier: Development Status :: 4 - Beta
Classifier: Framework :: Sphinx :: Extension
Classifier: Intended Audience :: Developers
Classifier: License :: OSI Approved :: BSD License
Classifier: Natural Language :: English
Classifier: Programming Language :: Python :: 3
Classifier: Topic :: Software Development :: Libraries :: Python Modules
Requires-Python: >=3.11
Requires-Dist: packaging
Requires-Dist: requests
Requires-Dist: sphinx
Requires-Dist: xdg
Provides-Extra: dev
Requires-Dist: furo; extra == 'dev'
Requires-Dist: pdbpp; extra == 'dev'
Requires-Dist: pre-commit; extra == 'dev'
Requires-Dist: pytest; extra == 'dev'
Requires-Dist: pytest-cov; extra == 'dev'
Requires-Dist: reuse; extra == 'dev'
Requires-Dist: ruff; extra == 'dev'
Requires-Dist: sphinx-argparse; extra == 'dev'
Requires-Dist: sphinx-autodoc-typehints; extra == 'dev'
Requires-Dist: sphinx-copybutton; extra == 'dev'
Requires-Dist: sphinx-inline-tabs; extra == 'dev'
Provides-Extra: doc
Requires-Dist: furo; extra == 'doc'
Requires-Dist: sphinx-argparse; extra == 'doc'
Requires-Dist: sphinx-autodoc-typehints; extra == 'doc'
Requires-Dist: sphinx-copybutton; extra == 'doc'
Requires-Dist: sphinx-inline-tabs; extra == 'doc'
Provides-Extra: qa
Requires-Dist: pre-commit; extra == 'qa'
Requires-Dist: reuse; extra == 'qa'
Requires-Dist: ruff; extra == 'qa'
Provides-Extra: test
Requires-Dist: pytest; extra == 'test'
Requires-Dist: pytest-cov; extra == 'test'
